cellmaps_image_embedding/__init__.py
cellmaps_image_embedding/cellmaps_image_embeddingcmd.py
cellmaps_image_embedding/dataset.py
cellmaps_image_embedding/exceptions.py
cellmaps_image_embedding/models.py
cellmaps_image_embedding/readme_outputs.txt
cellmaps_image_embedding/runner.py
cellmaps_image_embedding-0.3.3.data/scripts/cellmaps_image_embeddingcmd.py
cellmaps_image_embedding-0.3.3.dist-info/AUTHORS.rst
cellmaps_image_embedding-0.3.3.dist-info/LICENSE
cellmaps_image_embedding-0.3.3.dist-info/METADATA
cellmaps_image_embedding-0.3.3.dist-info/WHEEL
cellmaps_image_embedding-0.3.3.dist-info/top_level.txt
cellmaps_image_embedding-0.3.3.dist-info/RECORD
