Metadata-Version: 2.1
Name: cellmaps_image_embedding
Version: 0.3.3
Summary: A tool to generate embeddings from HPA IF images
Home-page: https://github.com/idekerlab/cellmaps_image_embedding
Author: Cell Maps team
Author-email: tools@cm4ai.org
License: MIT license
Keywords: cellmaps_image_embedding
Classifier: Development Status :: 2 - Pre-Alpha
Classifier: Intended Audience :: Developers
Classifier: License :: OSI Approved :: MIT License
Classifier: Natural Language :: English
Classifier: Programming Language :: Python :: 3.8
Classifier: Programming Language :: Python :: 3.9
Classifier: Programming Language :: Python :: 3.10
Classifier: Programming Language :: Python :: 3.11
License-File: LICENSE
License-File: AUTHORS.rst
Requires-Dist: cellmaps-utils <1.0.0,>=0.4.0
Requires-Dist: requests <3.0.0,>=2.31.0
Requires-Dist: tqdm <5.0.0,>=4.66.6
Requires-Dist: numpy <2.0.0,>=1.24.4
Requires-Dist: pandas <3.0.0,>=2.0.0
Requires-Dist: torch <3.0.0,>=2.0.0
Requires-Dist: torchvision <1.0.0,>=0.15.0
Requires-Dist: opencv-python <4.10,>=4.9.0.80
Requires-Dist: mlcrate ==0.2.0
Requires-Dist: scikit-image <1.0.0,>=0.21.0
Requires-Dist: scikit-learn <1.4.0,>=0.19.0
Requires-Dist: pillow <11.0.0,>=10.2.0
